pufferlib/_C.cpython-311-darwin.so
pufferlib/__init__.py
pufferlib/emulation.py
pufferlib/models.py
pufferlib/pufferl.py
pufferlib/pufferlib.py
pufferlib/pytorch.py
pufferlib/spaces.py
pufferlib/sweep.py
pufferlib/vector.py
pufferlib/extensions/pufferlib.cpp
pufferlib_core-3.0.10.dist-info/METADATA
pufferlib_core-3.0.10.dist-info/WHEEL
pufferlib_core-3.0.10.dist-info/top_level.txt
pufferlib_core-3.0.10.dist-info/RECORD
