Metadata-Version: 2.4
Name: pufferlib-core
Version: 3.0.10
Summary: PufferLib core functionality with vectorized environments and reinforcement learning
Author-email: Joseph Suarez <jsuarez@openai.com>
License-Expression: MIT
Project-URL: Homepage, https://github.com/PufferAI/PufferLib
Project-URL: Documentation, https://puffer.ai
Project-URL: Repository, https://github.com/PufferAI/PufferLib
Project-URL: Issues, https://github.com/PufferAI/PufferLib/issues
Keywords: reinforcement-learning,machine-learning,multi-agent,vectorized-environments
Classifier: Development Status :: 5 - Production/Stable
Classifier: Environment :: Console
Classifier: Intended Audience :: Developers
Classifier: Intended Audience :: Education
Classifier: Intended Audience :: Science/Research
Classifier: Operating System :: OS Independent
Classifier: Programming Language :: Python :: 3
Classifier: Programming Language :: Python :: 3.8
Classifier: Programming Language :: Python :: 3.9
Classifier: Programming Language :: Python :: 3.10
Classifier: Programming Language :: Python :: 3.11
Classifier: Programming Language :: Python :: 3.12
Classifier: Topic :: Scientific/Engineering :: Artificial Intelligence
Classifier: Topic :: Software Development :: Libraries :: Python Modules
Requires-Python: >=3.8
Requires-Dist: numpy
Requires-Dist: gymnasium
Requires-Dist: psutil
Requires-Dist: torch
Requires-Dist: nvidia-ml-py
Requires-Dist: rich
Requires-Dist: rich-argparse
Requires-Dist: setuptools
Requires-Dist: pyro-ppl
